.DS_Store
address_formatter/__init__.py
address_formatter/main.py
address_formatter/version.py
cwaddressformatter/.DS_Store
cwaddressformatter/__init__.py
cwaddressformatter/main.py
cwaddressformatter/opendata111road.csv
cwaddressformatter/version.py
cwaddressformatter-0.1.5.dist-info/METADATA
cwaddressformatter-0.1.5.dist-info/WHEEL
cwaddressformatter-0.1.5.dist-info/entry_points.txt
cwaddressformatter-0.1.5.dist-info/top_level.txt
cwaddressformatter-0.1.5.dist-info/RECORD
