Metadata-Version: 2.1
Name: cwaddressformatter
Version: 0.1.5
Summary: Format address using universal pattern
Home-page: https://github.com/Shihyen/address-formatter
Author: Shihyen Chen
Author-email: sun1229@gmail.com
License: UNKNOWN
Platform: UNKNOWN
Classifier: Programming Language :: Python
Classifier: Programming Language :: Python :: 2
Classifier: Programming Language :: Python :: 2.7
Classifier: Programming Language :: Python :: 3
Classifier: Programming Language :: Python :: 3.4
Classifier: Programming Language :: Python :: 3.5
Classifier: Programming Language :: Python :: 3.6
Classifier: License :: OSI Approved :: MIT License
Classifier: Operating System :: OS Independent
